Genie/__init__.py
Genie_STT-0.1.dist-info/METADATA
Genie_STT-0.1.dist-info/WHEEL
Genie_STT-0.1.dist-info/top_level.txt
Genie_STT-0.1.dist-info/RECORD
